README
setup.py
django_group_access/__init__.py
django_group_access/admin.py
django_group_access/middleware.py
django_group_access/models.py
django_group_access/registration.py
django_group_access/tests.py
django_group_access/testutil.py
django_group_access/views.py
django_group_access.egg-info/PKG-INFO
django_group_access.egg-info/SOURCES.txt
django_group_access.egg-info/dependency_links.txt
django_group_access.egg-info/requires.txt
django_group_access.egg-info/top_level.txt
django_group_access.egg-info/zip-safe
django_group_access/migrations/0001_initial.py
django_group_access/migrations/__init__.py